openwrt_luci_rpc/__init__.py
openwrt_luci_rpc/constants.py
openwrt_luci_rpc/exceptions.py
openwrt_luci_rpc/openwrt_luci_rpc.py
openwrt_luci_rpc/utilities.py
openwrt_luci_rpc-1.1.17.dist-info/AUTHORS.rst
openwrt_luci_rpc-1.1.17.dist-info/LICENSE
openwrt_luci_rpc-1.1.17.dist-info/METADATA
openwrt_luci_rpc-1.1.17.dist-info/WHEEL
openwrt_luci_rpc-1.1.17.dist-info/top_level.txt
openwrt_luci_rpc-1.1.17.dist-info/RECORD
