Metadata-Version: 1.1
Name: openwrt-luci-rpc
Version: 1.1.17
Summary: Module for interacting with OpenWrt Luci RPC interface
Home-page: https://github.com/fbradyirl/openwrt-luci-rpc
Author: Finbarr Brady
Author-email: fbradyirl@github.io
License: Apache Software License 2.0
Keywords: openwrt-luci-rpc
Platform: UNKNOWN
Classifier: Development Status :: 2 - Pre-Alpha
Classifier: Intended Audience :: Developers
Classifier: License :: OSI Approved :: Apache Software License
Classifier: Natural Language :: English
Classifier: Programming Language :: Python :: 3.7
